bitcaviar/__helpers.py
bitcaviar/__init__.py
bitcaviar/blockchain.py
bitcaviar/config.py
bitcaviar-0.0.2.dist-info/LICENSE.md
bitcaviar-0.0.2.dist-info/METADATA
bitcaviar-0.0.2.dist-info/WHEEL
bitcaviar-0.0.2.dist-info/top_level.txt
bitcaviar-0.0.2.dist-info/RECORD
