Metadata-Version: 2.1
Name: bitcaviar
Version: 0.0.2
Summary: A simple Python wrapper for Bitcoin JSON-RPC API
Home-page: https://github.com/denniscm190/bitcaviar
Author: Dennis Concepción Martín
Author-email: dennisconcepcionmartin@gmail.com
License: UNKNOWN
Project-URL: Bug Tracker, https://github.com/denniscm190/bitcaviar/issues
Platform: UNKNOWN
Classifier: Programming Language :: Python :: 3
Classifier: License :: OSI Approved :: MIT License
Classifier: Operating System :: OS Independent
Requires-Python: >=3.8
License-File: LICENSE.md
